{
  "colors": {
    "light": {
      "primary": {
        "value": "#0D2872",
        "hsl": "222 79% 25%",
        "usage": "Main brand color, primary CTAs, important UI elements"
      },
      "primaryForeground": {
        "value": "#fafafa",
        "hsl": "0 0% 98%",
        "usage": "Text on primary backgrounds"
      },
      "secondary": {
        "value": "#355EC4",
        "hsl": "222 57% 49%",
        "usage": "Secondary actions, links, less prominent CTAs"
      },
      "secondaryForeground": {
        "value": "#fafafa",
        "hsl": "0 0% 98%",
        "usage": "Text on secondary backgrounds"
      },
      "accent": {
        "value": "#FFBE00",
        "hsl": "45 100% 50%",
        "usage": "Highlights, badges, attention-grabbing elements"
      },
      "accentForeground": {
        "value": "#171717",
        "hsl": "0 0% 9%",
        "usage": "Text on accent backgrounds"
      },
      "background": {
        "value": "#ffffff",
        "hsl": "0 0% 100%",
        "usage": "Page background"
      },
      "foreground": {
        "value": "#0a0a0a",
        "hsl": "0 0% 4%",
        "usage": "Primary text color"
      },
      "card": {
        "value": "#ffffff",
        "hsl": "0 0% 100%",
        "usage": "Card backgrounds"
      },
      "cardForeground": {
        "value": "#0a0a0a",
        "hsl": "0 0% 4%",
        "usage": "Text on cards"
      },
      "popover": {
        "value": "#ffffff",
        "hsl": "0 0% 100%",
        "usage": "Popover/dropdown backgrounds"
      },
      "popoverForeground": {
        "value": "#0a0a0a",
        "hsl": "0 0% 4%",
        "usage": "Text on popovers"
      },
      "muted": {
        "value": "#f5f5f5",
        "hsl": "0 0% 96%",
        "usage": "Muted backgrounds, disabled states"
      },
      "mutedForeground": {
        "value": "#737373",
        "hsl": "0 0% 45%",
        "usage": "Secondary text, placeholders"
      },
      "destructive": {
        "value": "#EF4444",
        "hsl": "0 84% 60%",
        "usage": "Error states, delete actions"
      },
      "destructiveForeground": {
        "value": "#fafafa",
        "hsl": "0 0% 98%",
        "usage": "Text on destructive backgrounds"
      },
      "border": {
        "value": "#e5e5e5",
        "hsl": "0 0% 90%",
        "usage": "Borders, dividers"
      },
      "input": {
        "value": "#e5e5e5",
        "hsl": "0 0% 90%",
        "usage": "Input borders"
      },
      "ring": {
        "value": "#0D2872",
        "hsl": "222 79% 25%",
        "usage": "Focus rings"
      },
      "surfaceElevated": {
        "value": "#f7f7f7",
        "hsl": "0 0% 97%",
        "usage": "Elevated surface backgrounds"
      },
      "surfaceOverlay": {
        "value": "rgba(255, 255, 255, 0.95)",
        "hsl": "0 0% 100% / 0.95",
        "usage": "Semi-transparent overlay surfaces"
      }
    },
    "dark": {
      "primary": {
        "value": "#355EC4",
        "hsl": "222 57% 49%",
        "usage": "Main brand color in dark mode"
      },
      "primaryForeground": {
        "value": "#fafafa",
        "hsl": "0 0% 98%",
        "usage": "Text on primary backgrounds"
      },
      "secondary": {
        "value": "#0D2872",
        "hsl": "222 79% 25%",
        "usage": "Secondary actions in dark mode"
      },
      "secondaryForeground": {
        "value": "#fafafa",
        "hsl": "0 0% 98%",
        "usage": "Text on secondary backgrounds"
      },
      "accent": {
        "value": "#FFBE00",
        "hsl": "45 100% 50%",
        "usage": "Highlights, badges"
      },
      "accentForeground": {
        "value": "#171717",
        "hsl": "0 0% 9%",
        "usage": "Text on accent backgrounds"
      },
      "background": {
        "value": "#0a0a0a",
        "hsl": "0 0% 4%",
        "usage": "Page background"
      },
      "foreground": {
        "value": "#fafafa",
        "hsl": "0 0% 98%",
        "usage": "Primary text color"
      },
      "card": {
        "value": "#0a0a0a",
        "hsl": "0 0% 4%",
        "usage": "Card backgrounds"
      },
      "cardForeground": {
        "value": "#fafafa",
        "hsl": "0 0% 98%",
        "usage": "Text on cards"
      },
      "popover": {
        "value": "#0a0a0a",
        "hsl": "0 0% 4%",
        "usage": "Popover/dropdown backgrounds"
      },
      "popoverForeground": {
        "value": "#fafafa",
        "hsl": "0 0% 98%",
        "usage": "Text on popovers"
      },
      "muted": {
        "value": "#262626",
        "hsl": "0 0% 15%",
        "usage": "Muted backgrounds, disabled states"
      },
      "mutedForeground": {
        "value": "#a3a3a3",
        "hsl": "0 0% 64%",
        "usage": "Secondary text, placeholders"
      },
      "destructive": {
        "value": "#7f1d1d",
        "hsl": "0 75% 31%",
        "usage": "Error states, delete actions"
      },
      "destructiveForeground": {
        "value": "#fafafa",
        "hsl": "0 0% 98%",
        "usage": "Text on destructive backgrounds"
      },
      "border": {
        "value": "#262626",
        "hsl": "0 0% 15%",
        "usage": "Borders, dividers"
      },
      "input": {
        "value": "#262626",
        "hsl": "0 0% 15%",
        "usage": "Input borders"
      },
      "ring": {
        "value": "#355EC4",
        "hsl": "222 57% 49%",
        "usage": "Focus rings"
      },
      "surfaceElevated": {
        "value": "#1a1a1a",
        "hsl": "0 0% 10%",
        "usage": "Elevated surface backgrounds in dark mode"
      },
      "surfaceOverlay": {
        "value": "rgba(10, 10, 10, 0.95)",
        "hsl": "0 0% 4% / 0.95",
        "usage": "Semi-transparent overlay surfaces in dark mode"
      }
    },
    "semantic": {
      "success": {
        "value": "#10b981",
        "hsl": "160 84% 39%",
        "usage": "Success states, positive feedback"
      },
      "warning": {
        "value": "#f59e0b",
        "hsl": "38 92% 50%",
        "usage": "Warning states, caution indicators"
      },
      "info": {
        "value": "#3b82f6",
        "hsl": "217 91% 60%",
        "usage": "Informational messages"
      },
      "error": {
        "value": "#ef4444",
        "hsl": "0 84% 60%",
        "usage": "Error messages, validation failures"
      }
    },
    "chart": {
      "chart1": {
        "value": "#0D2872",
        "usage": "Primary chart color"
      },
      "chart2": {
        "value": "#355EC4",
        "usage": "Secondary chart color"
      },
      "chart3": {
        "value": "#FFBE00",
        "usage": "Accent chart color"
      },
      "chart4": {
        "value": "#2d9f7e",
        "usage": "Fourth chart color"
      },
      "chart5": {
        "value": "#f59e0b",
        "usage": "Fifth chart color"
      }
    }
  },
  "typography": {
    "fonts": {
      "heading": {
        "family": "Space Grotesk",
        "fallback": "sans-serif",
        "weight": 700,
        "usage": "Headings, titles, hero text"
      },
      "body": {
        "family": "Inter",
        "fallback": "sans-serif",
        "weights": [400, 500, 600],
        "usage": "Body text, paragraphs, UI labels"
      }
    },
    "scale": {
      "xs": {
        "size": "0.75rem",
        "pixels": "12px",
        "lineHeight": "1rem",
        "usage": "Small labels, captions"
      },
      "sm": {
        "size": "0.875rem",
        "pixels": "14px",
        "lineHeight": "1.25rem",
        "usage": "Secondary text, buttons"
      },
      "base": {
        "size": "1rem",
        "pixels": "16px",
        "lineHeight": "1.5rem",
        "usage": "Body text"
      },
      "lg": {
        "size": "1.125rem",
        "pixels": "18px",
        "lineHeight": "1.75rem",
        "usage": "Large body text"
      },
      "xl": {
        "size": "1.25rem",
        "pixels": "20px",
        "lineHeight": "1.75rem",
        "usage": "Small headings"
      },
      "2xl": {
        "size": "1.5rem",
        "pixels": "24px",
        "lineHeight": "2rem",
        "usage": "Section headings"
      },
      "3xl": {
        "size": "1.875rem",
        "pixels": "30px",
        "lineHeight": "2.25rem",
        "usage": "Page headings"
      },
      "4xl": {
        "size": "2.25rem",
        "pixels": "36px",
        "lineHeight": "2.5rem",
        "usage": "Large page headings"
      },
      "5xl": {
        "size": "3rem",
        "pixels": "48px",
        "lineHeight": "1",
        "usage": "Hero headings"
      },
      "6xl": {
        "size": "3.75rem",
        "pixels": "60px",
        "lineHeight": "1",
        "usage": "Extra large hero headings"
      }
    },
    "weights": {
      "regular": 400,
      "medium": 500,
      "semibold": 600,
      "bold": 700
    },
    "effects": {
      "gradientPrimary": {
        "description": "Gradient text effect using brand colors",
        "css": "background: linear-gradient(135deg, hsl(222 79% 25%) 0%, hsl(222 57% 49%) 100%); -webkit-background-clip: text; -webkit-text-fill-color: transparent; background-clip: text;",
        "classes": "bg-gradient-to-r from-primary to-secondary bg-clip-text text-transparent",
        "usage": "Hero titles, emphasis text"
      },
      "gradientAccent": {
        "description": "Gradient text with accent color",
        "css": "background: linear-gradient(135deg, hsl(222 57% 49%) 0%, hsl(45 100% 50%) 100%); -webkit-background-clip: text; -webkit-text-fill-color: transparent; background-clip: text;",
        "classes": "bg-gradient-to-r from-secondary to-accent bg-clip-text text-transparent",
        "usage": "Call-to-action text, highlights"
      },
      "gradientCyan": {
        "description": "Cyan-teal gradient for modern look",
        "css": "background: linear-gradient(135deg, #06b6d4 0%, #14b8a6 100%); -webkit-background-clip: text; -webkit-text-fill-color: transparent; background-clip: text;",
        "classes": "bg-gradient-to-r from-cyan-500 to-teal-500 bg-clip-text text-transparent",
        "usage": "Tech-focused sections"
      },
      "textShadow": {
        "sm": "0 1px 2px rgba(0,0,0,0.1)",
        "md": "0 2px 4px rgba(0,0,0,0.1)",
        "lg": "0 4px 8px rgba(0,0,0,0.15)",
        "glow": "0 0 20px hsl(222 79% 25% / 0.3)",
        "usage": "Text emphasis on images or dark backgrounds"
      }
    }
  },
  "spacing": {
    "base": "4px",
    "scale": {
      "0": "0",
      "px": "1px",
      "0.5": "0.125rem",
      "1": "0.25rem",
      "1.5": "0.375rem",
      "2": "0.5rem",
      "2.5": "0.625rem",
      "3": "0.75rem",
      "3.5": "0.875rem",
      "4": "1rem",
      "5": "1.25rem",
      "6": "1.5rem",
      "7": "1.75rem",
      "8": "2rem",
      "9": "2.25rem",
      "10": "2.5rem",
      "11": "2.75rem",
      "12": "3rem",
      "14": "3.5rem",
      "16": "4rem",
      "20": "5rem",
      "24": "6rem",
      "28": "7rem",
      "32": "8rem",
      "36": "9rem",
      "40": "10rem",
      "44": "11rem",
      "48": "12rem",
      "52": "13rem",
      "56": "14rem",
      "60": "15rem",
      "64": "16rem",
      "72": "18rem",
      "80": "20rem",
      "96": "24rem"
    },
    "semantic": {
      "componentPadding": {
        "xs": "0.25rem",
        "sm": "0.5rem",
        "md": "1rem",
        "lg": "1.5rem",
        "xl": "2rem"
      },
      "sectionGap": {
        "sm": "1.5rem",
        "md": "2rem",
        "lg": "3rem",
        "xl": "4rem"
      }
    }
  },
  "borderRadius": {
    "none": "0",
    "sm": "0.125rem",
    "default": "0.5rem",
    "md": "0.375rem",
    "lg": "0.5rem",
    "xl": "0.75rem",
    "2xl": "1rem",
    "3xl": "1.5rem",
    "full": "9999px"
  },
  "shadows": {
    "sm": {
      "value": "0 1px 2px 0 rgb(0 0 0 / 0.05)",
      "usage": "Subtle elevation for cards, buttons"
    },
    "default": {
      "value": "0 1px 3px 0 rgb(0 0 0 / 0.1), 0 1px 2px -1px rgb(0 0 0 / 0.1)",
      "usage": "Standard elevation"
    },
    "md": {
      "value": "0 4px 6px -1px rgb(0 0 0 / 0.07), 0 2px 4px -2px rgb(0 0 0 / 0.05)",
      "usage": "Medium elevation for dropdowns, popovers"
    },
    "lg": {
      "value": "0 10px 15px -3px rgb(0 0 0 / 0.08), 0 4px 6px -4px rgb(0 0 0 / 0.05)",
      "usage": "High elevation for modals, dialogs"
    },
    "xl": {
      "value": "0 20px 25px -5px rgb(0 0 0 / 0.08), 0 8px 10px -6px rgb(0 0 0 / 0.05)",
      "usage": "Maximum elevation for floating elements"
    },
    "2xl": {
      "value": "0 25px 50px -12px rgb(0 0 0 / 0.25)",
      "usage": "Extra large elevation"
    },
    "inner": {
      "value": "inset 0 2px 4px 0 rgb(0 0 0 / 0.05)",
      "usage": "Inset shadows for inputs, pressed states"
    },
    "glow": {
      "primary": {
        "value": "0 0 40px hsl(222 79% 25% / 0.15)",
        "usage": "Glow effect for primary elements"
      },
      "primaryStrong": {
        "value": "0 0 60px hsl(222 79% 25% / 0.25)",
        "usage": "Strong glow for hero elements"
      },
      "cyan": {
        "value": "0 0 40px hsl(172 79% 41% / 0.3)",
        "usage": "Cyan/teal glow for interactive landing page elements"
      },
      "cyanStrong": {
        "value": "0 0 60px hsl(172 79% 41% / 0.5)",
        "usage": "Strong cyan glow for hero CTAs and emphasis"
      },
      "button": {
        "default": "shadow-lg shadow-primary/20",
        "hover": "shadow-xl shadow-primary/30",
        "usage": "Button shadow with brand color tint"
      },
      "card": {
        "gradient": "radial-gradient(circle at 50% 0%, var(--color)15, transparent 70%)",
        "usage": "Subtle top glow effect on card hover - replace var(--color) with actual color"
      }
    }
  },
  "animations": {
    "durations": {
      "fast": "150ms",
      "normal": "300ms",
      "slow": "500ms"
    },
    "easings": {
      "default": "ease-in-out",
      "in": "ease-in",
      "out": "ease-out",
      "inOut": "ease-in-out",
      "linear": "linear"
    },
    "keyframes": {
      "fadeIn": {
        "from": { "opacity": 0 },
        "to": { "opacity": 1 },
        "duration": "0.5s",
        "easing": "ease-out"
      },
      "slideUp": {
        "from": { "opacity": 0, "transform": "translateY(30px)" },
        "to": { "opacity": 1, "transform": "translateY(0)" },
        "duration": "0.6s",
        "easing": "ease-out",
        "fillMode": "forwards",
        "usage": "Main entrance animation for titles and content blocks"
      },
      "scaleIn": {
        "from": { "opacity": 0, "transform": "scale(0.95)" },
        "to": { "opacity": 1, "transform": "scale(1)" },
        "duration": "0.4s",
        "easing": "ease-out"
      },
      "pulseGlow": {
        "0%": { "boxShadow": "0 0 20px hsl(222 79% 25% / 0.2)" },
        "50%": { "boxShadow": "0 0 40px hsl(222 79% 25% / 0.4)" },
        "100%": { "boxShadow": "0 0 20px hsl(222 79% 25% / 0.2)" },
        "duration": "2s",
        "easing": "ease-in-out",
        "iteration": "infinite"
      },
      "fadeInUp": {
        "from": { "opacity": 0, "transform": "translateY(40px)" },
        "to": { "opacity": 1, "transform": "translateY(0)" },
        "duration": "0.6s",
        "easing": "cubic-bezier(0.4, 0, 0.2, 1)",
        "fillMode": "forwards",
        "usage": "Card and list item entrance animation with more dramatic movement"
      },
      "spin": {
        "from": { "transform": "rotate(0deg)" },
        "to": { "transform": "rotate(360deg)" },
        "duration": "1s",
        "easing": "linear",
        "iteration": "infinite"
      },
      "pulse": {
        "0%": { "opacity": 1 },
        "50%": { "opacity": 0.5 },
        "100%": { "opacity": 1 },
        "duration": "2s",
        "easing": "ease-in-out",
        "iteration": "infinite"
      },
      "bounce": {
        "0%": { "transform": "translateY(-25%)", "animationTimingFunction": "cubic-bezier(0.8,0,1,1)" },
        "50%": { "transform": "translateY(0)", "animationTimingFunction": "cubic-bezier(0,0,0.2,1)" },
        "100%": { "transform": "translateY(-25%)", "animationTimingFunction": "cubic-bezier(0.8,0,1,1)" },
        "duration": "1s",
        "iteration": "infinite"
      },
      "accordionDown": {
        "from": { "height": "0" },
        "to": { "height": "var(--radix-accordion-content-height)" },
        "duration": "0.2s",
        "easing": "ease-out"
      },
      "accordionUp": {
        "from": { "height": "var(--radix-accordion-content-height)" },
        "to": { "height": "0" },
        "duration": "0.2s",
        "easing": "ease-out"
      },
      "shimmer": {
        "from": { "backgroundPosition": "-200% 0" },
        "to": { "backgroundPosition": "200% 0" },
        "duration": "1.5s",
        "easing": "linear",
        "iteration": "infinite",
        "usage": "Loading skeleton shimmer effect"
      },
      "float": {
        "0%": { "transform": "translateY(0px)" },
        "50%": { "transform": "translateY(-10px)" },
        "100%": { "transform": "translateY(0px)" },
        "duration": "3s",
        "easing": "ease-in-out",
        "iteration": "infinite",
        "usage": "Floating elements like hero images"
      },
      "slideInLeft": {
        "from": { "opacity": 0, "transform": "translateX(-30px)" },
        "to": { "opacity": 1, "transform": "translateX(0)" },
        "duration": "0.5s",
        "easing": "ease-out",
        "usage": "Elements entering from left"
      },
      "slideInRight": {
        "from": { "opacity": 0, "transform": "translateX(30px)" },
        "to": { "opacity": 1, "transform": "translateX(0)" },
        "duration": "0.5s",
        "easing": "ease-out",
        "usage": "Elements entering from right"
      },
      "slideInDown": {
        "from": { "opacity": 0, "transform": "translateY(-30px)" },
        "to": { "opacity": 1, "transform": "translateY(0)" },
        "duration": "0.5s",
        "easing": "ease-out",
        "usage": "Elements entering from top"
      },
      "wiggle": {
        "0%": { "transform": "rotate(0deg)" },
        "25%": { "transform": "rotate(-5deg)" },
        "50%": { "transform": "rotate(5deg)" },
        "75%": { "transform": "rotate(-5deg)" },
        "100%": { "transform": "rotate(0deg)" },
        "duration": "0.5s",
        "easing": "ease-in-out",
        "usage": "Attention-grabbing micro-interaction"
      },
      "heartbeat": {
        "0%": { "transform": "scale(1)" },
        "14%": { "transform": "scale(1.1)" },
        "28%": { "transform": "scale(1)" },
        "42%": { "transform": "scale(1.1)" },
        "70%": { "transform": "scale(1)" },
        "duration": "1.5s",
        "easing": "ease-in-out",
        "iteration": "infinite",
        "usage": "Pulsing attention element like notifications"
      },
      "countUp": {
        "description": "Number counting animation - implemented via JS",
        "duration": "2s",
        "easing": "ease-out",
        "usage": "Animating metric numbers on scroll into view"
      },
      "progressBar": {
        "from": { "width": "0%" },
        "to": { "width": "var(--progress-value)" },
        "duration": "1s",
        "easing": "ease-out",
        "usage": "Progress bar fill animation"
      },
      "typewriter": {
        "from": { "width": "0" },
        "to": { "width": "100%" },
        "duration": "3s",
        "easing": "steps(40)",
        "usage": "Typewriter text reveal effect"
      },
      "blink": {
        "0%": { "opacity": 1 },
        "50%": { "opacity": 0 },
        "100%": { "opacity": 1 },
        "duration": "1s",
        "iteration": "infinite",
        "usage": "Cursor blink for typewriter effect"
      }
    },
    "framerMotion": {
      "description": "Framer Motion animation presets for React components",
      "presets": {
        "fadeIn": {
          "initial": { "opacity": 0 },
          "animate": { "opacity": 1 },
          "transition": { "duration": 0.5 }
        },
        "fadeInUp": {
          "initial": { "opacity": 0, "y": 40 },
          "animate": { "opacity": 1, "y": 0 },
          "transition": { "duration": 0.6, "ease": [0.4, 0, 0.2, 1] }
        },
        "fadeInDown": {
          "initial": { "opacity": 0, "y": -20 },
          "animate": { "opacity": 1, "y": 0 },
          "transition": { "duration": 0.5, "ease": "easeOut" }
        },
        "fadeInLeft": {
          "initial": { "opacity": 0, "x": -20 },
          "animate": { "opacity": 1, "x": 0 },
          "transition": { "duration": 0.5, "ease": "easeOut" }
        },
        "fadeInRight": {
          "initial": { "opacity": 0, "x": 20 },
          "animate": { "opacity": 1, "x": 0 },
          "transition": { "duration": 0.5, "ease": "easeOut" }
        },
        "scaleIn": {
          "initial": { "opacity": 0, "scale": 0.95 },
          "animate": { "opacity": 1, "scale": 1 },
          "transition": { "duration": 0.4, "ease": "easeOut" }
        },
        "slideUp": {
          "initial": { "opacity": 0, "y": 30 },
          "animate": { "opacity": 1, "y": 0 },
          "transition": { "duration": 0.6, "ease": "easeOut" }
        },
        "staggerChildren": {
          "animate": { "transition": { "staggerChildren": 0.1 } }
        },
        "spring": {
          "transition": { "type": "spring", "stiffness": 300, "damping": 30 }
        },
        "hover": {
          "scale": 1.02,
          "transition": { "duration": 0.2 }
        },
        "hoverCard": {
          "scale": 1.02,
          "y": -4,
          "transition": { "duration": 0.3 }
        },
        "tap": {
          "scale": 0.98
        },
        "tapButton": {
          "scale": 0.95
        }
      },
      "viewportTrigger": {
        "description": "Animation triggered when element enters viewport",
        "once": true,
        "margin": "-100px"
      },
      "staggerPatterns": {
        "description": "Predefined stagger delay patterns for sequential animations",
        "cards": {
          "description": "For card grids - 100ms between each",
          "delayPerItem": 0.1,
          "example": "style={{ animationDelay: `${index * 100}ms` }}"
        },
        "hero": {
          "description": "Hero section elements - specific delays",
          "badge": 0,
          "logo": 0.05,
          "title": 0,
          "subtitle": 0.1,
          "description": 0.2,
          "cta": 0.3
        },
        "list": {
          "description": "List items - 50ms between each",
          "delayPerItem": 0.05
        }
      }
    }
  },
  "zIndex": {
    "auto": "auto",
    "base": 0,
    "dropdown": 10,
    "sticky": 20,
    "fixed": 30,
    "modalBackdrop": 40,
    "modal": 50,
    "popover": 60,
    "tooltip": 70
  },
  "breakpoints": {
    "sm": "640px",
    "md": "768px",
    "lg": "1024px",
    "xl": "1280px",
    "2xl": "1536px"
  },
  "containers": {
    "sm": "640px",
    "md": "768px",
    "lg": "1024px",
    "xl": "1280px",
    "maxWidth": "1280px",
    "padding": "1.5rem"
  }
}
